matplotlib_backend_pyside2/__init__.py
matplotlib_backend_pyside2/backend_qtquick.py
matplotlib_backend_pyside2/backend_qtquickagg.py
matplotlib_backend_pyside2-0.0.11.dist-info/licenses/LICENSE
matplotlib_backend_pyside2-0.0.11.dist-info/METADATA
matplotlib_backend_pyside2-0.0.11.dist-info/WHEEL
matplotlib_backend_pyside2-0.0.11.dist-info/top_level.txt
matplotlib_backend_pyside2-0.0.11.dist-info/RECORD
