Metadata-Version: 2.4
Name: matplotlib-backend-pyside2
Version: 0.0.11
Summary: Backend to use matplotlib in qml
Author-email: Nicklas Osmers <nosmers@qass.net>
Project-URL: Homepage, https://github.com/QASS/matplotlib-backend-pyside2
Classifier: Programming Language :: Python :: 3
Classifier: License :: OSI Approved :: GNU Lesser General Public License v3 (LGPLv3)
Classifier: Operating System :: OS Independent
Requires-Python: >=3.6
License-File: LICENSE
Requires-Dist: matplotlib>=3.3.3
Requires-Dist: matplotlib<3.7
Provides-Extra: pyside2
Requires-Dist: PySide2; extra == "pyside2"
Dynamic: license-file
